esibd/__init__.py
esibd/__main__.py
esibd/config.py
esibd/const.py
esibd/core.py
esibd/explorer.py
esibd/extended.py
esibd/plugins.py
esibd/provide_plugins.py
esibd/reset.py
esibd/devices/__init__.py
esibd/devices/__pycache__/__init__.cpython-311.pyc
esibd/devices/iseg/ISEG.png
esibd/devices/iseg/ISEG.xcf
esibd/devices/iseg/__init__.py
esibd/devices/iseg/iseg.py
esibd/devices/iseg/__pycache__/__init__.cpython-311.pyc
esibd/devices/iseg/__pycache__/iseg.cpython-311.pyc
esibd/devices/keithley/__init__.py
esibd/devices/keithley/battery-empty.png
esibd/devices/keithley/keithley.png
esibd/devices/keithley/keithley.py
esibd/devices/keithley/__pycache__/__init__.cpython-311.pyc
esibd/devices/keithley/__pycache__/keithley.cpython-311.pyc
esibd/devices/lakeshore335/335_manual 1.pdf
esibd/devices/lakeshore335/LS335.png
esibd/devices/lakeshore335/LS335.xcf
esibd/devices/lakeshore335/__init__.py
esibd/devices/lakeshore335/lakeshore.py
esibd/devices/lakeshore335/tempC_dark.png
esibd/devices/lakeshore335/tempC_light.png
esibd/devices/lakeshore335/tempK_dark.png
esibd/devices/lakeshore335/tempK_light.png
esibd/devices/lakeshore335/__pycache__/LAKESHORE335.cpython-311.pyc
esibd/devices/lakeshore335/__pycache__/__init__.cpython-311.pyc
esibd/devices/lakeshore335/__pycache__/lakeshore.cpython-311.pyc
esibd/devices/maxigauge/__init__.py
esibd/devices/maxigauge/maxigauge.py
esibd/devices/maxigauge/pfeiffer.png
esibd/devices/maxigauge/pfeiffer.xcf
esibd/devices/maxigauge/pfeiffer_maxi.png
esibd/devices/maxigauge/pfeiffer_omni.png
esibd/devices/maxigauge/__pycache__/__init__.cpython-311.pyc
esibd/devices/maxigauge/__pycache__/maxigauge.cpython-311.pyc
esibd/devices/mips/GAA.jpg
esibd/devices/mips/GAA.xcf
esibd/devices/mips/__init__.py
esibd/devices/mips/mips.png
esibd/devices/mips/mips.py
esibd/devices/mips/__pycache__/__init__.cpython-311.pyc
esibd/devices/mips/__pycache__/mips.cpython-311.pyc
esibd/devices/ni9263/NI.xcf
esibd/devices/ni9263/NI9263.png
esibd/devices/ni9263/__init__.py
esibd_explorer-0.8.2.dist-info/licenses/LICENSE
esibd_explorer-0.8.2.dist-info/METADATA
esibd_explorer-0.8.2.dist-info/WHEEL
esibd_explorer-0.8.2.dist-info/top_level.txt
esibd_explorer-0.8.2.dist-info/RECORD
