Metadata-Version: 2.4
Name: esibd-explorer
Version: 0.8.2
Summary: A comprehensive data acquisition and analysis tool for Electrospray Ion-Beam Deposition experiments and beyond.
Author-email: ioneater <ioneater.dev@gmail.com>
Project-URL: Homepage, https://esibd-explorer.readthedocs.io/en/stable/index.html
Project-URL: Source, https://github.com/ioneater/ESIBD-Explorer
Requires-Python: >=3.11
License-File: LICENSE
Requires-Dist: asteval
Requires-Dist: biopython
Requires-Dist: configobj
Requires-Dist: configparser
Requires-Dist: h5py
Requires-Dist: keyboard
Requires-Dist: matplotlib
Requires-Dist: contourpy==1.2.1
Requires-Dist: lakeshore
Requires-Dist: nidaqmx
Requires-Dist: numpy
Requires-Dist: requests
Requires-Dist: pfeiffer-vacuum-protocol
Requires-Dist: picosdk
Requires-Dist: opencv-python
Requires-Dist: openpyxl
Requires-Dist: PyOpenGL
Requires-Dist: pyperclip
Requires-Dist: pyqt6==6.6
Requires-Dist: pyqt6-qt6==6.6
Requires-Dist: pyqt6-webengine==6.6
Requires-Dist: pyqt6-webengine-qt6==6.6
Requires-Dist: python-pptx
Requires-Dist: pyserial
Requires-Dist: python-socketio
Requires-Dist: pyvisa
Requires-Dist: pywin32; sys_platform == "win32"
Requires-Dist: pyqtgraph==0.13.7
Requires-Dist: scipy
Requires-Dist: Send2Trash
Requires-Dist: simple_pid
Dynamic: license-file
